OpenSSL/SSL.py
OpenSSL/__init__.py
OpenSSL/_util.py
OpenSSL/crypto.py
OpenSSL/debug.py
OpenSSL/py.typed
OpenSSL/rand.py
OpenSSL/version.py
pyopenssl_qpython-24.2.1.dist-info/METADATA
pyopenssl_qpython-24.2.1.dist-info/WHEEL
pyopenssl_qpython-24.2.1.dist-info/top_level.txt
pyopenssl_qpython-24.2.1.dist-info/RECORD
